plc_module/__init__.py
plc_module/pyPLC_connected.py
plc_testmain_inline_mapping-1.0.0.dist-info/METADATA
plc_testmain_inline_mapping-1.0.0.dist-info/WHEEL
plc_testmain_inline_mapping-1.0.0.dist-info/top_level.txt
plc_testmain_inline_mapping-1.0.0.dist-info/RECORD
