Metadata-Version: 2.1
Name: plc_testmain_inline_mapping
Version: 1.0.0
Summary: Communication with PLC via serial connections
Keywords: communicates with PLC
Classifier: Intended Audience :: Developers
Classifier: Topic :: Software Development :: Libraries :: Python Modules
Classifier: Programming Language :: Python :: 3
Requires-Dist: pywin32>=306
Requires-Dist: pyserial>=3
